malibu/__init__.py
malibu/assessment.py
malibu/fib.py
malibu/malibu.py
malibu/my_mod.py
malibu/train.py
Malibu_lambda_3-0.0.3.dist-info/LICENSE
Malibu_lambda_3-0.0.3.dist-info/METADATA
Malibu_lambda_3-0.0.3.dist-info/WHEEL
Malibu_lambda_3-0.0.3.dist-info/top_level.txt
Malibu_lambda_3-0.0.3.dist-info/RECORD
