Metadata-Version: 2.1
Name: Malibu-lambda-3
Version: 0.0.3
Summary: package for lambda school Ds Unit 3
Home-page: https://github.com/Moly-malibu/paquetepy.git
Author: Monica Bustamante
Author-email: lilianalambda@gmail.com
License: MIT
Keywords: Paquete
Platform: UNKNOWN
